{
    "Accuracy": 0.8298714144411474,
    "Precision": 0.8349333379418485,
    "Recall": 0.8298714144411474,
    "F1 Score": 0.821536202925153,
    "Classification Report": {
        "Class metrics": {
            "meningioma": {
                "Precision": 0.85,
                "Recall": 0.58,
                "F1 Score": 0.68,
                "Support": 306
            },
            "notumor": {
                "Precision": 0.89,
                "Recall": 0.95,
                "F1 Score": 0.92,
                "Support": 405
            },
            "pituitary": {
                "Precision": 0.75,
                "Recall": 0.92,
                "F1 Score": 0.83,
                "Support": 300
            }
        },
        "Global metrics": {
            "accuracy": {
                "f1-score": 0.83,
                "support": 1011
            },
            "macro avg": {
                "precision": 0.83,
                "recall": 0.82,
                "f1-score": 0.81,
                "support": 1011
            },
            "weighted avg": {
                "precision": 0.83,
                "recall": 0.83,
                "f1-score": 0.82,
                "support": 1011
            }
        }
    }
}